evillimiter/__init__.py
evillimiter/evillimiter.py
evillimiter/common/__init__.py
evillimiter/common/globals.py
evillimiter/console/__init__.py
evillimiter/console/banner.py
evillimiter/console/chart.py
evillimiter/console/io.py
evillimiter/console/shell.py
evillimiter/menus/__init__.py
evillimiter/menus/main_menu.py
evillimiter/menus/menu.py
evillimiter/menus/parser.py
evillimiter/networking/__init__.py
evillimiter/networking/host.py
evillimiter/networking/limit.py
evillimiter/networking/monitor.py
evillimiter/networking/scan.py
evillimiter/networking/spoof.py
evillimiter/networking/utils.py
evillimiter/networking/watch.py
evillimiter-1.5.1.dist-info/LICENSE
evillimiter-1.5.1.dist-info/METADATA
evillimiter-1.5.1.dist-info/WHEEL
evillimiter-1.5.1.dist-info/entry_points.txt
evillimiter-1.5.1.dist-info/top_level.txt
evillimiter-1.5.1.dist-info/RECORD
